burnlight/__init__.py
burnlight/block.py
burnlight/channels.py
burnlight/client.py
burnlight/program.py
burnlight/programparser.py
burnlight/rpigpio.py
burnlight/scheduler.py
burnlight/server.py
burnlight/client/__init__.py
burnlight/client/client.py
burnlight/server/__init__.py
burnlight/server/server.py
burnlight-0.2.0.dist-info/LICENSE
burnlight-0.2.0.dist-info/METADATA
burnlight-0.2.0.dist-info/WHEEL
burnlight-0.2.0.dist-info/entry_points.txt
burnlight-0.2.0.dist-info/top_level.txt
burnlight-0.2.0.dist-info/RECORD
