Metadata-Version: 2.1
Name: burnlight
Version: 0.2.0
Summary: GPIO scheduler for Raspberry Pis
Home-page: https://github.com/wailashi/burnlight
Author: Matthew Casserly
Author-email: 
License: MIT
Platform: UNKNOWN
Classifier: License :: OSI Approved :: MIT License
Classifier: Programming Language :: Python :: 3
Requires-Dist: flask (>=1.0.0)
Requires-Dist: lark-parser
Requires-Dist: gevent
Requires-Dist: click
Requires-Dist: gpiozero
Requires-Dist: requests
